satmad/__init__.py
satmad/coordinates/__init__.py
satmad/coordinates/frames.py
satmad/coordinates/planetary_rot_elems.py
satmad/coordinates/trajectory.py
satmad/coordinates/data/.gitignore
satmad/coordinates/tests/__init__.py
satmad/coordinates/tests/test_baseframe_transform.py
satmad/coordinates/tests/test_trajectory.py
satmad/core/__init__.py
satmad/core/celestial_bodies_lib.py
satmad/core/celestial_body.py
satmad/core/ground_location.py
satmad/core/occultation.py
satmad/core/tests/__init__.py
satmad/core/tests/test_central_body.py
satmad/core/tests/test_ground_location.py
satmad/core/tests/test_occultation.py
satmad/data/README.rst
satmad/plots/__init__.py
satmad/plots/basic_plots.py
satmad/plots/plotstyling.py
satmad/propagation/__init__.py
satmad/propagation/base_propagator.py
satmad/propagation/classical_orb_elems.py
satmad/propagation/force_models.py
satmad/propagation/numerical_propagators.py
satmad/propagation/sgp4_propagator.py
satmad/propagation/tle.py
satmad/propagation/tle_storage.py
satmad/propagation/tests/__init__.py
satmad/propagation/tests/num_prop_analysis_engine.py
satmad/propagation/tests/test_classical_orb_elems.py
satmad/propagation/tests/test_num_propagators.py
satmad/propagation/tests/test_sgp4.py
satmad/propagation/tests/test_tle.py
satmad/propagation/tests/test_tle_storage.py
satmad/propagation/tests/data/tle_mixed_1.txt
satmad/propagation/tests/data/tle_rasat.txt
satmad/propagation/tests/data/tle_rasat_desc.txt
satmad/tests/__init__.py
satmad/tests/common_test_funcs.py
satmad/tests/data/.gitignore
satmad/utils/__init__.py
satmad/utils/discrete_time_events.py
satmad/utils/interpolators.py
satmad/utils/timeinterval.py
satmad/utils/tests/__init__.py
satmad/utils/tests/test_events.py
satmad/utils/tests/test_timeinterval.py
satmad-0.1.2.dist-info/LICENSE.rst
satmad-0.1.2.dist-info/WHEEL
satmad-0.1.2.dist-info/METADATA
satmad-0.1.2.dist-info/RECORD
