Metadata-Version: 2.1
Name: satmad
Version: 0.1.2
Summary: satmad
Home-page: https://github.com/egemenimre/satmad/
Keywords: satellite,satellite design,mission analysis,aerospace,engineering,astrodynamics,orbits,orbital mechanics
Author: Egemen Imre
Classifier: Intended Audience :: Science/Research
Classifier: License :: OSI Approved :: GNU General Public License v3 or later (GPLv3+)
Classifier: Operating System :: OS Independent
Classifier: Programming Language :: Python
Classifier: Programming Language :: Python :: 3
Classifier: Topic :: Scientific/Engineering
Classifier: Topic :: Scientific/Engineering :: Physics
Requires-Dist: astropy
Requires-Dist: jplephem
Requires-Dist: matplotlib
Requires-Dist: numpy
Requires-Dist: portion
Requires-Dist: pyerfa
Requires-Dist: scipy
Requires-Dist: sgp4
Requires-Dist: sphinx ; extra == "doc"
Requires-Dist: pytest ; extra == "test"
Requires-Dist: pytest-cov ; extra == "test"
Requires-Dist: pytest-xdist ; extra == "test"
Project-URL: Documentation, https://satmad.readthedocs.io/en/latest/
Provides-Extra: doc
Provides-Extra: test
